odoo/addons/stock_account_change_qty_reason/README.rst
odoo/addons/stock_account_change_qty_reason/__init__.py
odoo/addons/stock_account_change_qty_reason/__manifest__.py
odoo/addons/stock_account_change_qty_reason/i18n/stock_account_change_qty_reason.pot
odoo/addons/stock_account_change_qty_reason/models/__init__.py
odoo/addons/stock_account_change_qty_reason/models/stock_inventory_line_reason.py
odoo/addons/stock_account_change_qty_reason/models/stock_move.py
odoo/addons/stock_account_change_qty_reason/readme/CONFIGURE.rst
odoo/addons/stock_account_change_qty_reason/readme/CONTRIBUTORS.rst
odoo/addons/stock_account_change_qty_reason/readme/DESCRIPTION.rst
odoo/addons/stock_account_change_qty_reason/static/description/icon.png
odoo/addons/stock_account_change_qty_reason/static/description/index.html
odoo/addons/stock_account_change_qty_reason/tests/__init__.py
odoo/addons/stock_account_change_qty_reason/tests/test_stock_account_change_qty_reason.py
odoo/addons/stock_account_change_qty_reason/views/stock_inventory_line_reason_view.xml
odoo/addons/stock_account_change_qty_reason/views/stock_move_view.xml
odoo11_addon_stock_account_change_qty_reason-11.0.1.0.0.99.dev4.dist-info/METADATA
odoo11_addon_stock_account_change_qty_reason-11.0.1.0.0.99.dev4.dist-info/WHEEL
odoo11_addon_stock_account_change_qty_reason-11.0.1.0.0.99.dev4.dist-info/top_level.txt
odoo11_addon_stock_account_change_qty_reason-11.0.1.0.0.99.dev4.dist-info/RECORD
